torchaug/__init__.py
torchaug/_utils.py
torchaug/data/__init__.py
torchaug/data/dataloader/__init__.py
torchaug/data/dataloader/_collate.py
torchaug/data/dataset/__init__.py
torchaug/data/dataset/_dataset_wrapper.py
torchaug/ta_tensors/__init__.py
torchaug/ta_tensors/_batch_bounding_boxes.py
torchaug/ta_tensors/_batch_concatenated_ta_tensor.py
torchaug/ta_tensors/_batch_images.py
torchaug/ta_tensors/_batch_labels.py
torchaug/ta_tensors/_batch_masks.py
torchaug/ta_tensors/_batch_videos.py
torchaug/ta_tensors/_bounding_boxes.py
torchaug/ta_tensors/_image.py
torchaug/ta_tensors/_labels.py
torchaug/ta_tensors/_mask.py
torchaug/ta_tensors/_registry.py
torchaug/ta_tensors/_ta_tensor.py
torchaug/ta_tensors/_torch_function_helpers.py
torchaug/ta_tensors/_video.py
torchaug/ta_tensors/_wrap.py
torchaug/ta_tensors/nested/__init__.py
torchaug/ta_tensors/nested/_bounding_boxes.py
torchaug/ta_tensors/nested/_image.py
torchaug/ta_tensors/nested/_labels.py
torchaug/ta_tensors/nested/_mask.py
torchaug/ta_tensors/nested/_ta_nested_tensors.py
torchaug/ta_tensors/nested/_tensor.py
torchaug/ta_tensors/nested/_video.py
torchaug/transforms/__init__.py
torchaug/transforms/_augment.py
torchaug/transforms/_auto_augment.py
torchaug/transforms/_color.py
torchaug/transforms/_container.py
torchaug/transforms/_geometry.py
torchaug/transforms/_meta.py
torchaug/transforms/_misc.py
torchaug/transforms/_temporal.py
torchaug/transforms/_transform.py
torchaug/transforms/_type_conversion.py
torchaug/transforms/_utils.py
torchaug/transforms/functional/__init__.py
torchaug/transforms/functional/_augment.py
torchaug/transforms/functional/_color.py
torchaug/transforms/functional/_geometry.py
torchaug/transforms/functional/_meta.py
torchaug/transforms/functional/_misc.py
torchaug/transforms/functional/_temporal.py
torchaug/transforms/functional/_type_conversion.py
torchaug/transforms/functional/_utils/__init__.py
torchaug/transforms/functional/_utils/_kernel.py
torchaug-0.6.1.dist-info/LICENSE
torchaug-0.6.1.dist-info/METADATA
torchaug-0.6.1.dist-info/WHEEL
torchaug-0.6.1.dist-info/top_level.txt
torchaug-0.6.1.dist-info/zip-safe
torchaug-0.6.1.dist-info/RECORD
