Metadata-Version: 2.2
Name: torchaug
Version: 0.6.1
Summary: Torchvision Complementary tool to perform batch and GPU data augmentations.
Author-email: Julien Denize <julien.denize@cea.fr>
Project-URL: Bug Tracker, https://github.com/juliendenize/torchaug/issues
Project-URL: Download, https://github.com/juliendenize/torchaug
Project-URL: Homepage, https://github.com/juliendenize/torchaug
Project-URL: Source Code, https://github.com/juliendenize/torchaug
Keywords: computer vision,deep learning,pytorch
Classifier: Development Status :: 4 - Beta
Classifier: Environment :: Console
Classifier: Environment :: GPU
Classifier: Intended Audience :: Developers
Classifier: Intended Audience :: Education
Classifier: Intended Audience :: Information Technology
Classifier: Intended Audience :: Science/Research
Classifier: License :: CeCILL-C Free Software License Agreement (CECILL-C)
Classifier: Natural Language :: English
Classifier: Operating System :: OS Independent
Classifier: Programming Language :: Python :: 3 :: Only
Classifier: Programming Language :: Python :: 3.8
Classifier: Programming Language :: Python :: 3.9
Classifier: Programming Language :: Python :: 3.10
Classifier: Programming Language :: Python :: 3.11
Classifier: Programming Language :: Python :: 3.12
Classifier: Topic :: Scientific/Engineering :: Artificial Intelligence
Classifier: Topic :: Scientific/Engineering :: Image Processing
Classifier: Topic :: Software Development :: Libraries
Requires-Python: <3.13,>=3.8
License-File: LICENSE
Requires-Dist: torchvision<0.20,>=0.17.0
